{
  "ErrorDesc": "",
  "HotelList": {
    "HG121572": {
      "Address1": "New International Airport Road",
      "Address2": "",
      "Address3": "",
      "APPriority": 42,
      "APPriorityGIF": "",
      "BillBackIndicator": "",
      "BlacklistedFlag": "N",
      "BOPropertyFlag": "N",
      "CacheMaxRate": 8400.55,
      "CacheMinRate": 6720.19,
      "CacheMinRateCurrency": "EUR",
      "CacheMinRateDttm": "2015-10-04T18:30:00Z",
      "ChainCode": "CB24",
      "CityCode": "190347",
      "CityDesc": "Chikkajala",
      "CountryCode": "IN",
      "CountryDesc": "India",
      "CPPriority": 100,
      "CPPriorityGIF": "",
      "Distance": [
        {
          "Distance": 7.795905032342842,
          "From": "POI",
          "IATA": "",
          "To": "Goldfinch Retreat",
          "Type": 0
        },
        {
          "Distance": 1.6103874935297233,
          "From": "Goldfinch Retreat",
          "IATA": "BLR",
          "To": "Chikkajala",
          "Type": 1
        }
      ],
      "EmailId": "test.bookings@tctmail.com",
      "Fax": "+918042408720",
      "Facility": "",
      "FaxFormat": "IN|91|8042408720",
      "GlobalRegionCode": "APAC",
      "HostPropertyId": "293147",
      "HotelCode": "AX190429",
      "HotelGroupFlag": "",
      "HotelHubCode": "HG121572",
      "HotelName": "Goldfinch Retreat",
      "HotelRating": 0,
      "HotelRemarks": "",
      "HotelReviewCount": 0,
      "IATA": "BLR",
      "IntelReviewCount": "1",
      "IntelReviewScore": "2",
      "KmsDistance": 7.795905032342842,
      "Latitude": 13.18599,
      "Longitude": 77.63577,
      "OnRequestLink": "Y",
      "ParticipatingChannels": "BC,EH",
      "PostCode": "562157",
      "propertyType": "RES",
      "ProvinceCode": "KA",
      "ProvinceDesc": "Karnataka",
      "StarRating": "4 Star",
      "StarRatingCode": "4",
      "Telephone": "+918022011500",
      "TelephoneFormat": "IN|91|8022011500",
      "facilitiesInfo": null,
      "CountryChannelBlockingFlag": "N",
      "HotelChainChannelBlockingFlag": "N",
      "facilityInfo": [],
      "GuestRating": 0,
      "GuestRatingCount": 0,
      "Usage": "Y",
      "IsHHAllocation": "",
      "OnRequestHotel": "false",
      "ThumbnailUrl": "https://i.travelapi.com/hotels/5000000/4940000/4937000/4936933/e729cd47_t.jpg",
      "HygieneInfo": "",
      "MetaphoneHotelName": "",
      "providerInfo": [
        {
          "id": "",
          "provider": "",
          "chainCode": ""
        }
      ]
    },
    "BC175432": {
      "Address1": "Brigade Orchards Kasaba Hobili",
      "Address2": "",
      "Address3": "",
      "APPriority": 44,
      "APPriorityGIF": "",
      "BillBackIndicator": "",
      "BlacklistedFlag": "N",
      "BOPropertyFlag": "N",
      "CacheMaxRate": 0,
      "CacheMinRate": 0,
      "CacheMinRateCurrency": "",
      "ChainCode": "CB24",
      "CityCode": "179811",
      "CityDesc": "Devanhalli",
      "CountryCode": "IN",
      "CountryDesc": "India",
      "CPPriority": 100,
      "CPPriorityGIF": "",
      "Distance": [
        {
          "Distance": 3.104404679161592,
          "From": "POI",
          "IATA": "",
          "To": "Signature Club Resort",
          "Type": 0
        },
        {
          "Distance": 7987.734070977217,
          "From": "Signature Club Resort",
          "IATA": "BLR",
          "To": "Devanhalli",
          "Type": 1
        }
      ],
      "EmailId": "",
      "Fax": "",
      "Facility": "",
      "FaxFormat": "",
      "GlobalRegionCode": "APAC",
      "HostPropertyId": "814257",
      "HotelCode": "BC175432",
      "HotelGroupFlag": "",
      "HotelHubCode": "BC175432",
      "HotelName": "Signature Club Resort",
      "HotelRating": 0,
      "HotelRemarks": "",
      "HotelReviewCount": 0,
      "IATA": "BLR",
      "IntelReviewCount": "1",
      "IntelReviewScore": "5",
      "KmsDistance": 3.104404679161592,
      "Latitude": 13.22777,
      "Longitude": 77.7209,
      "OnRequestLink": "Y",
      "ParticipatingChannels": "BC,EH,HE,HR",
      "PostCode": "562110",
      "propertyType": "HOT",
      "ProvinceCode": "",
      "ProvinceDesc": "",
      "StarRating": "4 Star",
      "StarRatingCode": "4",
      "Telephone": "+918023086688",
      "TelephoneFormat": "IN|91|8023086688",
      "facilitiesInfo": null,
      "CountryChannelBlockingFlag": "N",
      "HotelChainChannelBlockingFlag": "N",
      "facilityInfo": [],
      "GuestRating": 0,
      "GuestRatingCount": 0,
      "Usage": "N",
      "IsHHAllocation": "",
      "OnRequestHotel": "false",
      "ThumbnailUrl": "https://i.travelapi.com/hotels/16000000/15820000/15813100/15813048/73ddfd11_t.jpg",
      "HygieneInfo": "",
      "MetaphoneHotelName": "",
      "providerInfo": [
        {
          "id": "",
          "provider": "",
          "chainCode": ""
        }
      ]
    },
    "HC080464": {
      "Address1": "Swiss Town",
      "Address2": "Hollywood Junction Sadahalli P",
      "Address3": "",
      "APPriority": 51,
      "APPriorityGIF": "",
      "BillBackIndicator": "",
      "BlacklistedFlag": "N",
      "BOPropertyFlag": "N",
      "CacheMaxRate": 34159.27,
      "CacheMinRate": 7378.4,
      "CacheMinRateCurrency": "EUR",
      "CacheMinRateDttm": "2015-10-04T18:30:00Z",
      "ChainCode": "GL88",
      "CityCode": "812",
      "CityDesc": "Bangalore",
      "CountryCode": "IN",
      "CountryDesc": "India",
      "CPPriority": 100,
      "CPPriorityGIF": "",
      "Distance": [
        {
          "Distance": 7.7560301474438615,
          "From": "POI",
          "IATA": "",
          "To": "Clarks Exotica Resort and Spa",
          "Type": 0
        },
        {
          "Distance": 26.45859850526158,
          "From": "Clarks Exotica Resort and Spa",
          "IATA": "BLR",
          "To": "Bangalore",
          "Type": 1
        }
      ],
      "EmailId": "test.bookings@tctmail.com",
      "Fax": "+918042408720",
      "Facility": "",
      "FaxFormat": "IN|91|8042408720",
      "GlobalRegionCode": "APAC",
      "HostPropertyId": "345240",
      "HotelCode": "AX68372",
      "HotelGroupFlag": "",
      "HotelHubCode": "HC080464",
      "HotelName": "Clarks Exotica Resort and Spa",
      "HotelRating": 0,
      "HotelRemarks": "",
      "HotelReviewCount": 0,
      "IATA": "BLR",
      "IntelReviewCount": "",
      "IntelReviewScore": "",
      "KmsDistance": 7.7560301474438615,
      "Latitude": 13.20622,
      "Longitude": 77.6336,
      "OnRequestLink": "Y",
      "ParticipatingChannels": "A,BC,EH,HE,HR",
      "PostCode": "562110",
      "propertyType": "RES",
      "ProvinceCode": "KA",
      "ProvinceDesc": "Karnataka",
      "StarRating": "5 Star",
      "StarRatingCode": "5",
      "Telephone": "+918071777000",
      "TelephoneFormat": "IN|91|8071777000",
      "facilitiesInfo": null,
      "CountryChannelBlockingFlag": "N",
      "HotelChainChannelBlockingFlag": "N",
      "facilityInfo": [],
      "GuestRating": 0,
      "GuestRatingCount": 0,
      "Usage": "N",
      "IsHHAllocation": "",
      "OnRequestHotel": "false",
      "ThumbnailUrl": "https://q-xx.bstatic.com/xdata/images/hotel/max300/162437201.jpg?k=b077ef5dbe7e51afe87fe185e55e15fb29e7703fd2ec39fa20704ceb4f97752c&o=",
      "HygieneInfo": "",
      "MetaphoneHotelName": "",
      "providerInfo": [
        {
          "id": "CEH",
          "provider": "A",
          "chainCode": "PH"
        }
      ]
    },
    "HF524345": {
      "Address1": "Plot No 12 A Hegganahalli Village Kundana Hoblidevanahalli Taluk Bangalore North",
      "Address2": "",
      "Address3": "",
      "APPriority": 86,
      "APPriorityGIF": "",
      "BillBackIndicator": "",
      "BlacklistedFlag": "N",
      "BOPropertyFlag": "N",
      "CacheMaxRate": 0,
      "CacheMinRate": 0,
      "CacheMinRateCurrency": "",
      "CacheMinRateDttm": "0001-01-01T00:00:00Z",
      "ChainCode": "A403",
      "CityCode": "179811",
      "CityDesc": "Devanhalli",
      "CountryCode": "IN",
      "CountryDesc": "India",
      "CPPriority": 100,
      "CPPriorityGIF": "",
      "Distance": [
        {
          "Distance": 10.518835843891903,
          "From": "POI",
          "IATA": "",
          "To": "The Windflower Prakruthi Bangalore",
          "Type": 0
        },
        {
          "Distance": 7987.931099995129,
          "From": "The Windflower Prakruthi Bangalore",
          "IATA": "BLR",
          "To": "Devanhalli",
          "Type": 1
        }
      ],
      "EmailId": "",
      "Fax": "",
      "Facility": "",
      "FaxFormat": "",
      "GlobalRegionCode": "APAC",
      "HostPropertyId": "781472",
      "HotelCode": "BC94508",
      "HotelGroupFlag": "",
      "HotelHubCode": "HF524345",
      "HotelName": "The Windflower Prakruthi Bangalore",
      "HotelRating": 0,
      "HotelRemarks": "",
      "HotelReviewCount": 0,
      "IATA": "BLR",
      "IntelReviewCount": "",
      "IntelReviewScore": "",
      "KmsDistance": 10.518835843891903,
      "Latitude": 13.20314,
      "Longitude": 77.60809,
      "OnRequestLink": "Y",
      "ParticipatingChannels": "A,BC,HE",
      "PostCode": "562110",
      "propertyType": "RES",
      "ProvinceCode": "",
      "ProvinceDesc": "",
      "StarRating": "3 Star",
      "StarRatingCode": "3",
      "Telephone": "+918049015777",
      "TelephoneFormat": "IN|91|8049015777",
      "facilitiesInfo": null,
      "CountryChannelBlockingFlag": "N",
      "HotelChainChannelBlockingFlag": "N",
      "facilityInfo": [],
      "GuestRating": 0,
      "GuestRatingCount": 0,
      "Usage": "N",
      "IsHHAllocation": "",
      "OnRequestHotel": "false",
      "ThumbnailUrl": "",
      "HygieneInfo": "",
      "MetaphoneHotelName": "",
      "providerInfo": [
        {
          "id": "WIN",
          "provider": "A",
          "chainCode": "YX"
        }
      ]
    },
    "BC462465": {
      "Address1": "Awho Vasanth Vihar P 4 Villa No 32 Near Svit College Vidyanagar Cross",
      "Address2": "",
      "Address3": "",
      "APPriority": 89,
      "APPriorityGIF": "",
      "BillBackIndicator": "",
      "BlacklistedFlag": "N",
      "BOPropertyFlag": "N",
      "CacheMaxRate": 0,
      "CacheMinRate": 0,
      "CacheMinRateCurrency": "",
      "CacheMinRateDttm": "0001-01-01T00:00:00Z",
      "ChainCode": "AX12",
      "CityCode": "156725",
      "CityDesc": "Yelahanka",
      "CountryCode": "IN",
      "CountryDesc": "India",
      "CPPriority": 100,
      "CPPriorityGIF": "",
      "Distance": [
        {
          "Distance": 8.91553281308079,
          "From": "POI",
          "IATA": "",
          "To": "Villa 32",
          "Type": 0
        },
        {
          "Distance": 2.1668836993308367,
          "From": "Villa 32",
          "IATA": "BLR",
          "To": "Yelahanka",
          "Type": 1
        }
      ],
      "EmailId": "",
      "Fax": "",
      "Facility": "",
      "FaxFormat": "",
      "GlobalRegionCode": "APAC",
      "HostPropertyId": "",
      "HotelCode": "BC462465",
      "HotelGroupFlag": "",
      "HotelHubCode": "BC462465",
      "HotelName": "Villa 32",
      "HotelRating": 0,
      "HotelRemarks": "",
      "HotelReviewCount": 0,
      "IATA": "BLR",
      "IntelReviewCount": "",
      "IntelReviewScore": "",
      "KmsDistance": 8.91553281308079,
      "Latitude": 13.15403,
      "Longitude": 77.64126,
      "OnRequestLink": "Y",
      "ParticipatingChannels": "BC",
      "PostCode": "560099",
      "propertyType": "HOT",
      "ProvinceCode": "KA",
      "ProvinceDesc": "Karnataka",
      "StarRating": "Unclassified",
      "StarRatingCode": "0",
      "Telephone": "+919742320002",
      "TelephoneFormat": "IN|91|9742320002",
      "facilitiesInfo": null,
      "CountryChannelBlockingFlag": "N",
      "HotelChainChannelBlockingFlag": "N",
      "facilityInfo": [],
      "GuestRating": 0,
      "GuestRatingCount": 0,
      "Usage": "N",
      "IsHHAllocation": "",
      "OnRequestHotel": "false",
      "ThumbnailUrl": "",
      "HygieneInfo": "",
      "MetaphoneHotelName": "",
      "providerInfo": [
        {
          "id": "",
          "provider": "",
          "chainCode": ""
        }
      ]
    },
    "BC148141": {
      "Address1": "81 Hunsemarenhalli Next To Viva Toyota Showroom New Airport Road",
      "Address2": "",
      "Address3": "",
      "APPriority": 89,
      "APPriorityGIF": "",
      "BillBackIndicator": "",
      "BlacklistedFlag": "N",
      "BOPropertyFlag": "N",
      "CacheMaxRate": 0,
      "CacheMinRate": 0,
      "CacheMinRateCurrency": "",
      "CacheMinRateDttm": "0001-01-01T00:00:00Z",
      "ChainCode": "AX12",
      "CityCode": "156725",
      "CityDesc": "Yelahanka",
      "CountryCode": "IN",
      "CountryDesc": "India",
      "CPPriority": 100,
      "CPPriorityGIF": "",
      "Distance": [
        {
          "Distance": 11.212179267594978,
          "From": "POI",
          "IATA": "",
          "To": "Hotel Airport Comfort",
          "Type": 0
        },
        {
          "Distance": 2.412276304901695,
          "From": "Hotel Airport Comfort",
          "IATA": "BLR",
          "To": "Yelahanka",
          "Type": 1
        }
      ],
      "EmailId": "",
      "Fax": "",
      "Facility": "",
      "FaxFormat": "",
      "GlobalRegionCode": "APAC",
      "HostPropertyId": "784759",
      "HotelCode": "BC148141",
      "HotelGroupFlag": "",
      "HotelHubCode": "BC148141",
      "HotelName": "Hotel Airport Comfort",
      "HotelRating": 0,
      "HotelRemarks": "",
      "HotelReviewCount": 0,
      "IATA": "BLR",
      "IntelReviewCount": "",
      "IntelReviewScore": "",
      "KmsDistance": 11.212179267594978,
      "Latitude": 13.14785,
      "Longitude": 77.6196,
      "OnRequestLink": "Y",
      "ParticipatingChannels": "",
      "PostCode": "562157",
      "propertyType": "HOT",
      "ProvinceCode": "KA",
      "ProvinceDesc": "Karnataka",
      "StarRating": "Unclassified",
      "StarRatingCode": "0",
      "Telephone": "+919901450876",
      "TelephoneFormat": "IN|91|9901450876",
      "facilitiesInfo": null,
      "CountryChannelBlockingFlag": "N",
      "HotelChainChannelBlockingFlag": "N",
      "facilityInfo": [],
      "GuestRating": 0,
      "GuestRatingCount": 0,
      "Usage": "N",
      "IsHHAllocation": "",
      "OnRequestHotel": "false",
      "ThumbnailUrl": "",
      "HygieneInfo": "",
      "MetaphoneHotelName": "",
      "providerInfo": [
        {
          "id": "",
          "provider": "",
          "chainCode": ""
        }
      ]
    },
    "BC454935": {
      "Address1": "5th Cross Road No 5",
      "Address2": "",
      "Address3": "",
      "APPriority": 89,
      "APPriorityGIF": "",
      "BillBackIndicator": "",
      "BlacklistedFlag": "N",
      "BOPropertyFlag": "N",
      "CacheMaxRate": 0,
      "CacheMinRate": 0,
      "CacheMinRateCurrency": "",
      "CacheMinRateDttm": "0001-01-01T00:00:00Z",
      "ChainCode": "AX12",
      "CityCode": "193569",
      "CityDesc": "Jalahalli",
      "CountryCode": "IN",
      "CountryDesc": "India",
      "CPPriority": 100,
      "CPPriorityGIF": "",
      "Distance": [
        {
          "Distance": 16.066916074321927,
          "From": "POI",
          "IATA": "",
          "To": "Escape Gardens",
          "Type": 0
        },
        {
          "Distance": 14.170768254305186,
          "From": "Escape Gardens",
          "IATA": "BLR",
          "To": "Jalahalli",
          "Type": 1
        }
      ],
      "EmailId": "",
      "Fax": "",
      "Facility": "",
      "FaxFormat": "",
      "GlobalRegionCode": "APAC",
      "HostPropertyId": "",
      "HotelCode": "BC454935",
      "HotelGroupFlag": "",
      "HotelHubCode": "BC454935",
      "HotelName": "Escape Gardens",
      "HotelRating": 0,
      "HotelRemarks": "",
      "HotelReviewCount": 0,
      "IATA": "BLR",
      "IntelReviewCount": "",
      "IntelReviewScore": "",
      "KmsDistance": 16.066916074321927,
      "Latitude": 13.07376,
      "Longitude": 77.64231,
      "OnRequestLink": "Y",
      "ParticipatingChannels": "",
      "PostCode": "560077",
      "propertyType": "HOT",
      "ProvinceCode": "KA",
      "ProvinceDesc": "Karnataka",
      "StarRating": "Unclassified",
      "StarRatingCode": "0",
      "Telephone": "+919742222212",
      "TelephoneFormat": "IN|91|9742222212",
      "facilitiesInfo": null,
      "CountryChannelBlockingFlag": "N",
      "HotelChainChannelBlockingFlag": "N",
      "facilityInfo": [],
      "GuestRating": 0,
      "GuestRatingCount": 0,
      "Usage": "N",
      "IsHHAllocation": "",
      "OnRequestHotel": "false",
      "ThumbnailUrl": "",
      "HygieneInfo": "",
      "MetaphoneHotelName": "",
      "providerInfo": [
        {
          "id": "",
          "provider": "",
          "chainCode": ""
        }
      ]
    },
    "BC419673": {
      "Address1": "Gkvk Layout Yerthaganahalli",
      "Address2": "",
      "Address3": "",
      "APPriority": 89,
      "APPriorityGIF": "",
      "BillBackIndicator": "",
      "BlacklistedFlag": "N",
      "BOPropertyFlag": "N",
      "CacheMaxRate": 0,
      "CacheMinRate": 0,
      "CacheMinRateCurrency": "",
      "CacheMinRateDttm": "0001-01-01T00:00:00Z",
      "ChainCode": "AX12",
      "CityCode": "179811",
      "CityDesc": "Devanhalli",
      "CountryCode": "IN",
      "CountryDesc": "India",
      "CPPriority": 100,
      "CPPriorityGIF": "",
      "Distance": [
        {
          "Distance": 3.7672126524271325,
          "From": "POI",
          "IATA": "",
          "To": "Airport Residency Bangalore",
          "Type": 0
        },
        {
          "Distance": 7990.834153174824,
          "From": "Airport Residency Bangalore",
          "IATA": "BLR",
          "To": "Devanhalli",
          "Type": 1
        }
      ],
      "EmailId": "",
      "Fax": "",
      "Facility": "",
      "FaxFormat": "",
      "GlobalRegionCode": "APAC",
      "HostPropertyId": "",
      "HotelCode": "BC419673",
      "HotelGroupFlag": "",
      "HotelHubCode": "BC419673",
      "HotelName": "Airport Residency Bangalore",
      "HotelRating": 0,
      "HotelRemarks": "",
      "HotelReviewCount": 0,
      "IATA": "BLR",
      "IntelReviewCount": "",
      "IntelReviewScore": "",
      "KmsDistance": 3.7672126524271325,
      "Latitude": 13.1898,
      "Longitude": 77.67383,
      "OnRequestLink": "Y",
      "ParticipatingChannels": "",
      "PostCode": "562157",
      "propertyType": "HOT",
      "ProvinceCode": "",
      "ProvinceDesc": "",
      "StarRating": "3 Star",
      "StarRatingCode": "3",
      "Telephone": "+919845610866",
      "TelephoneFormat": "IN|91|9845610866",
      "facilitiesInfo": null,
      "CountryChannelBlockingFlag": "N",
      "HotelChainChannelBlockingFlag": "N",
      "facilityInfo": [],
      "GuestRating": 0,
      "GuestRatingCount": 0,
      "Usage": "N",
      "IsHHAllocation": "",
      "OnRequestHotel": "false",
      "ThumbnailUrl": "",
      "HygieneInfo": "",
      "MetaphoneHotelName": "",
      "providerInfo": [
        {
          "id": "",
          "provider": "",
          "chainCode": ""
        }
      ]
    },
    "BC396553": {
      "Address1": "Sadahalli Road and Gate No 15 Down Town Park",
      "Address2": "",
      "Address3": "",
      "APPriority": 89,
      "APPriorityGIF": "",
      "BillBackIndicator": "",
      "BlacklistedFlag": "N",
      "BOPropertyFlag": "N",
      "CacheMaxRate": 0,
      "CacheMinRate": 0,
      "CacheMinRateCurrency": "",
      "CacheMinRateDttm": "0001-01-01T00:00:00Z",
      "ChainCode": "AX12",
      "CityCode": "812",
      "CityDesc": "Bangalore",
      "CountryCode": "IN",
      "CountryDesc": "India",
      "CPPriority": 100,
      "CPPriorityGIF": "",
      "Distance": [
        {
          "Distance": 6.575122091684443,
          "From": "POI",
          "IATA": "",
          "To": "Regenta Inn by Royal Orchid Hotels Ltd",
          "Type": 0
        },
        {
          "Distance": 25.128118820685824,
          "From": "Regenta Inn by Royal Orchid Hotels Ltd",
          "IATA": "BLR",
          "To": "Bangalore",
          "Type": 1
        }
      ],
      "EmailId": "",
      "Fax": "",
      "Facility": "",
      "FaxFormat": "",
      "GlobalRegionCode": "APAC",
      "HostPropertyId": "",
      "HotelCode": "BC396553",
      "HotelGroupFlag": "",
      "HotelHubCode": "BC396553",
      "HotelName": "Regenta Inn by Royal Orchid Hotels Ltd",
      "HotelRating": 0,
      "HotelRemarks": "",
      "HotelReviewCount": 0,
      "IATA": "BLR",
      "IntelReviewCount": "",
      "IntelReviewScore": "",
      "KmsDistance": 6.575122091684443,
      "Latitude": 13.19172,
      "Longitude": 77.6459,
      "OnRequestLink": "Y",
      "ParticipatingChannels": "BC",
      "PostCode": "562157",
      "propertyType": "HOT",
      "ProvinceCode": "KA",
      "ProvinceDesc": "Karnataka",
      "StarRating": "Unclassified",
      "StarRatingCode": "0",
      "Telephone": "+918028477555",
      "TelephoneFormat": "IN|91|8028477555",
      "facilitiesInfo": null,
      "CountryChannelBlockingFlag": "N",
      "HotelChainChannelBlockingFlag": "N",
      "facilityInfo": [],
      "GuestRating": 0,
      "GuestRatingCount": 0,
      "Usage": "N",
      "IsHHAllocation": "",
      "OnRequestHotel": "false",
      "ThumbnailUrl": "",
      "HygieneInfo": "",
      "MetaphoneHotelName": "",
      "providerInfo": [
        {
          "id": "",
          "provider": "",
          "chainCode": ""
        }
      ]
    },
    "HH722826": {
      "Address1": "842 Swiss Sadahalli Post Devanahalli Rd",
      "Address2": "",
      "Address3": "",
      "APPriority": 89,
      "APPriorityGIF": "",
      "BillBackIndicator": "",
      "BlacklistedFlag": "N",
      "BOPropertyFlag": "N",
      "CacheMaxRate": 0,
      "CacheMinRate": 0,
      "CacheMinRateCurrency": "",
      "CacheMinRateDttm": "0001-01-01T00:00:00Z",
      "ChainCode": "AX12",
      "CityCode": "812",
      "CityDesc": "Bangalore",
      "CountryCode": "IN",
      "CountryDesc": "India",
      "CPPriority": 100,
      "CPPriorityGIF": "",
      "Distance": [
        {
          "Distance": 8.160467772393428,
          "From": "POI",
          "IATA": "",
          "To": "Calista Manor",
          "Type": 0
        },
        {
          "Distance": 26.64767603847837,
          "From": "Calista Manor",
          "IATA": "BLR",
          "To": "Bangalore",
          "Type": 1
        }
      ],
      "EmailId": "",
      "Fax": "",
      "Facility": "",
      "FaxFormat": "",
      "GlobalRegionCode": "APAC",
      "HostPropertyId": "",
      "HotelCode": "HH722826",
      "HotelGroupFlag": "",
      "HotelHubCode": "HH722826",
      "HotelName": "Calista Manor",
      "HotelRating": 0,
      "HotelRemarks": "",
      "HotelReviewCount": 0,
      "IATA": "BLR",
      "IntelReviewCount": "",
      "IntelReviewScore": "",
      "KmsDistance": 8.160467772393428,
      "Latitude": 13.20848,
      "Longitude": 77.62996,
      "OnRequestLink": "Y",
      "ParticipatingChannels": "BC",
      "PostCode": "562110",
      "propertyType": "HOT",
      "ProvinceCode": "KA",
      "ProvinceDesc": "Karnataka",
      "StarRating": "5 Star",
      "StarRatingCode": "5",
      "Telephone": "+919663343466",
      "TelephoneFormat": "IN|91|9663343466",
      "facilitiesInfo": null,
      "CountryChannelBlockingFlag": "N",
      "HotelChainChannelBlockingFlag": "N",
      "facilityInfo": [],
      "GuestRating": 0,
      "GuestRatingCount": 0,
      "Usage": "N",
      "IsHHAllocation": "",
      "OnRequestHotel": "false",
      "ThumbnailUrl": "",
      "HygieneInfo": "",
      "MetaphoneHotelName": "",
      "providerInfo": [
        {
          "id": "",
          "provider": "",
          "chainCode": ""
        }
      ]
    }
  },
  "TotalHotels": 53,
  "TotalPopularHotels": 0,
  "TotalAlternativeHotels": 0,
  "blockedHotelList": [
    {
      "HotelCode": "HH164809",
      "HotelName": "Deltrum Riviera",
      "BlockingType": "Property Type Blocking"
    }
  ]
}